{"FZ4XpXvJwL2K96f0y4bfbA==":"mbr-1400x1050.jpg","bYmRUe3SloFDWeM7TkitRA==":"mbr-1920x1280.jpg","NkmT7WFodD3Iv9Zry5kK5w==":"011_3180x2090_all-free-download.com-2000x1314.jpg","VlZ4UgUQHHmfP9ILTKTDEQ==":"011_3180x2090_all-free-download.com-2000x1314.jpeg","GkuBUUaC+EnhmNEmPyh7Fg==":"011_3180x2090_all-free-download.com-1-2000x1314.jpeg","C5UeGk0DblOqSaPY475+zA==":"mbr-1400x700.jpg","wUIE1mjl818NdBiL5I5qmQ==":"mbr-1920x1278.jpg","9h8huVDN3rEuWCQVZImFuw==":"mbr-1400x933.jpg","901OPBV2Ac1+szZZDodZaw==":"blur-chart-check-up-curve-415779-1280x853.jpg","r121jwrbUpCNTozPmWQ/2g==":"mbr-1-1400x933.jpg","+z6sx8ueFeM3SyjXPW8r3g==":"mbr-1920x1279.jpg","6zHru1El2/p3F6HiCi6hMA==":"mbr-600x400.jpg","lPWbbvoYfQaaKyAGll1iJw==":"mbr-1-600x400.jpg","8tZktJXdT8d505aMd1y30Q==":"mbr-600x397.jpg","/kPs22Ti17OP0469Gksx1w==":"surgeon-in-the-operating-room-3845127-600x900.jpg","mge51A7yJGFizqyXiwRFjQ==":"person-holding-container-with-seaweed-2280568-1280x854.jpg","MFTJidb8+6ogbmetv0amtQ==":"thermometer-on-medical-pills-139398-1280x853.jpg","wdFZE+awW0yTgRQaqhBSFw==":"pain-armchair-dentist-suffering-52527-1280x847.jpg","omKffC0429wWKVt8wAI8Bw==":"mbr-1-1920x1279.jpg","i6TkhQm+NqKh1C87xqTDKA==":"brain-3168269-1280-1280x771.png","CW7MerqnisYKnBh5Z/StiQ==":"mbr-600x600.png","V3MTAcor+iy2EPkPaUX/jA==":"mbr-1400x1400.png","1+bjJ3o9q3E/t42XihWZLA==":"mbr-1-1920x1280.jpg","eIFMC7izYF3fgSaeCM2oyg==":"mbr-2-1920x1280.jpg","h1sMlfF/knpYiDa1Bu8opQ==":"mbr-160x160.png","sklUw4yPJiORe05XXpNjDg==":"mbr-1-160x160.png","qTuExdq9fvAPt9PKnzOxkw==":"mbr-2-160x160.png","DkwUe2huZutJ/ZK6C+OrtA==":"mbr-160x152.png","/Rc7rxF9cbWAjsdPzsAQkA==":"mbr-2-1920x1279.jpg","+R9HPs+Z3Fz12sl0ZBSkqw==":"mbr-1920x1285.jpg","2VNSTwOE1gUOp5EDDvCCZg==":"doctor-and-nurse-operating-on-a-patient-3844585-1280x853.jpg","bYneJ0XKINqgnxXLcv7PLQ==":"logo.png"}